coucal/__init__.py
coucal/_language.py
coucal/_options.py
coucal/aggregate.py
coucal/climate.py
coucal/version.py
coucal-0.0.1b3.dist-info/LICENSE
coucal-0.0.1b3.dist-info/METADATA
coucal-0.0.1b3.dist-info/WHEEL
coucal-0.0.1b3.dist-info/top_level.txt
coucal-0.0.1b3.dist-info/RECORD
